classiq_interface/__init__.py
classiq_interface/_version.py
classiq_interface/analyzer/analysis_params.py
classiq_interface/analyzer/result.py
classiq_interface/backend/backend_preferences.py
classiq_interface/backend/ionq/ionq_quantum_program.py
classiq_interface/backend/pydantic_backend.py
classiq_interface/backend/quantum_backend_providers.py
classiq_interface/chemistry/ansatz_library.py
classiq_interface/chemistry/elements.py
classiq_interface/chemistry/execute_chemistry_problem.py
classiq_interface/chemistry/ground_state_problem.py
classiq_interface/chemistry/molecule.py
classiq_interface/chemistry/operator.py
classiq_interface/combinatorial_optimization/encoding_types.py
classiq_interface/combinatorial_optimization/examples/ascending_sequence.py
classiq_interface/combinatorial_optimization/examples/ilp.py
classiq_interface/combinatorial_optimization/examples/integer_portfolio_optimization.py
classiq_interface/combinatorial_optimization/examples/knapsack.py
classiq_interface/combinatorial_optimization/examples/maxcut.py
classiq_interface/combinatorial_optimization/examples/mds.py
classiq_interface/combinatorial_optimization/examples/mht.py
classiq_interface/combinatorial_optimization/examples/mis.py
classiq_interface/combinatorial_optimization/examples/mvc.py
classiq_interface/combinatorial_optimization/examples/portfolio_optimization.py
classiq_interface/combinatorial_optimization/examples/portfolio_variations.py
classiq_interface/combinatorial_optimization/examples/set_cover.py
classiq_interface/combinatorial_optimization/examples/tsp.py
classiq_interface/combinatorial_optimization/examples/tsp_digraph.py
classiq_interface/combinatorial_optimization/mht_qaoa_input.py
classiq_interface/combinatorial_optimization/model_io_comon.py
classiq_interface/combinatorial_optimization/model_parser.py
classiq_interface/combinatorial_optimization/model_serializer.py
classiq_interface/combinatorial_optimization/optimization_problem.py
classiq_interface-0.8.1.dist-info/WHEEL
classiq_interface-0.8.1.dist-info/METADATA
classiq_interface-0.8.1.dist-info/RECORD
